trayifier/__init__.py
trayifier/__main__.py
trayifier/config.toml
Trayifier-1.2.3.dist-info/LICENSE
Trayifier-1.2.3.dist-info/METADATA
Trayifier-1.2.3.dist-info/WHEEL
Trayifier-1.2.3.dist-info/entry_points.txt
Trayifier-1.2.3.dist-info/top_level.txt
Trayifier-1.2.3.dist-info/RECORD
