Metadata-Version: 2.1
Name: Trayifier
Version: 1.2.3
Summary: Hide any program's window and create a tray icon for it.
Author: Silun
License: Apache License
Project-URL: Homepage, https://github.com/Silun/Trayify
Keywords: tray,tool,icon,tray icon
Classifier: License :: OSI Approved :: Apache Software License
Classifier: Programming Language :: Python
Classifier: Programming Language :: Python :: 3
Classifier: Environment :: Win32 (MS Windows)
Classifier: Intended Audience :: End Users/Desktop
Classifier: Topic :: Desktop Environment
Requires-Python: >=3.6
License-File: LICENSE
Requires-Dist: pywin32
Requires-Dist: PySimpleGUIWx
Requires-Dist: icoextract
Requires-Dist: tomli
